example_package/__init__.py
example_package/example.py
opencell-0.0.0.dist-info/LICENSE.txt
opencell-0.0.0.dist-info/METADATA
opencell-0.0.0.dist-info/WHEEL
opencell-0.0.0.dist-info/top_level.txt
opencell-0.0.0.dist-info/RECORD
