Metadata-Version: 2.1
Name: opencell
Version: 0.0.0
Summary: Proteome-scale measurements of human protein localization and interactions
Home-page: https://opencell.czbiohub.org
Author: 
Author-email: 
License: UNKNOWN
Platform: UNKNOWN
Classifier: Programming Language :: Python :: 3
Classifier: License :: OSI Approved :: BSD License
Classifier: Operating System :: OS Independent
Requires-Python: >=3.6
